inference_gym/__init__.py
inference_gym/using_jax.py
inference_gym/using_numpy.py
inference_gym/using_tensorflow.py
inference_gym/version.py
inference_gym/backends/__init__.py
inference_gym/backends/jax_integration_test.py
inference_gym/backends/numpy_integration_test.py
inference_gym/backends/rewrite.py
inference_gym/backends/tensorflow_integration_test.py
inference_gym/backends/util.py
inference_gym/dynamic/__init__.py
inference_gym/dynamic/backend_jax/__init__.py
inference_gym/dynamic/backend_numpy/__init__.py
inference_gym/dynamic/backend_tensorflow/__init__.py
inference_gym/internal/__init__.py
inference_gym/internal/array_to_source.py
inference_gym/internal/array_to_source_test.py
inference_gym/internal/data.py
inference_gym/internal/data_test.py
inference_gym/internal/ground_truth_encoding.py
inference_gym/internal/ground_truth_encoding_test.py
inference_gym/internal/test_util.py
inference_gym/internal/test_util_test.py
inference_gym/internal/datasets/__init__.py
inference_gym/internal/datasets/brownian_motion_missing_middle_observations.py
inference_gym/internal/datasets/convection_lorenz_bridge.py
inference_gym/internal/datasets/sp500_closing_prices.py
inference_gym/internal/datasets/synthetic_item_response_theory.py
inference_gym/internal/datasets/synthetic_log_gaussian_cox_process.py
inference_gym/internal/datasets/synthetic_plasma_spectroscopy.py
inference_gym/internal/datasets/synthetic_plasma_spectroscopy_with_bump.py
inference_gym/targets/__init__.py
inference_gym/targets/banana.py
inference_gym/targets/banana_test.py
inference_gym/targets/bayesian_model.py
inference_gym/targets/bayesian_model_test.py
inference_gym/targets/brownian_motion.py
inference_gym/targets/brownian_motion_test.py
inference_gym/targets/eight_schools.py
inference_gym/targets/eight_schools_test.py
inference_gym/targets/ill_conditioned_gaussian.py
inference_gym/targets/ill_conditioned_gaussian_test.py
inference_gym/targets/item_response_theory.py
inference_gym-0.0.5.dist-info/METADATA
inference_gym-0.0.5.dist-info/WHEEL
inference_gym-0.0.5.dist-info/top_level.txt
inference_gym-0.0.5.dist-info/RECORD
